{
"meta":{"test_sets":[],"test_metrics":[],"learn_metrics":[{"best_value":"Min","name":"Logloss"}],"launch_mode":"Train","parameters":"","iteration_count":259,"learn_sets":["learn"],"name":"experiment"},
"iterations":[
{"learn":[0.4641364397],"iteration":0,"passed_time":0.03531355995,"remaining_time":9.110898468},
{"learn":[0.3647671825],"iteration":1,"passed_time":0.07548902063,"remaining_time":9.700339151},
{"learn":[0.304333503],"iteration":2,"passed_time":0.1276895576,"remaining_time":10.89617558},
{"learn":[0.2659350169],"iteration":3,"passed_time":0.1796183866,"remaining_time":11.45067215},
{"learn":[0.2435694439],"iteration":4,"passed_time":0.2300601375,"remaining_time":11.68705498},
{"learn":[0.2294441882],"iteration":5,"passed_time":0.2811443565,"remaining_time":11.85492037},
{"learn":[0.212417598],"iteration":6,"passed_time":0.330878688,"remaining_time":11.91163277},
{"learn":[0.2059426019],"iteration":7,"passed_time":0.3753557972,"remaining_time":11.77678814},
{"learn":[0.2003645994],"iteration":8,"passed_time":0.4148220779,"remaining_time":11.5228355},
{"learn":[0.1961338195],"iteration":9,"passed_time":0.4619060115,"remaining_time":11.50145969},
{"learn":[0.1870769434],"iteration":10,"passed_time":0.5145360124,"remaining_time":11.60044828},
{"learn":[0.1778393865],"iteration":11,"passed_time":0.5724233891,"remaining_time":11.78238143},
{"learn":[0.1754399666],"iteration":12,"passed_time":0.6266967519,"remaining_time":11.85903084},
{"learn":[0.1712837411],"iteration":13,"passed_time":0.6693208901,"remaining_time":11.71311558},
{"learn":[0.1651728219],"iteration":14,"passed_time":0.7068738316,"remaining_time":11.49848099},
{"learn":[0.1613452366],"iteration":15,"passed_time":0.7440758123,"remaining_time":11.3006514},
{"learn":[0.1582390965],"iteration":16,"passed_time":0.7847480457,"remaining_time":11.17111924},
{"learn":[0.1549171324],"iteration":17,"passed_time":0.8283017915,"remaining_time":11.09004065},
{"learn":[0.1494199999],"iteration":18,"passed_time":0.8714246756,"remaining_time":11.00746959},
{"learn":[0.1451646362],"iteration":19,"passed_time":0.9211283783,"remaining_time":11.00748412},
{"learn":[0.1435719758],"iteration":20,"passed_time":0.9619480666,"remaining_time":10.90207809},
{"learn":[0.1417747403],"iteration":21,"passed_time":1.000085625,"remaining_time":10.77364969},
{"learn":[0.1402942642],"iteration":22,"passed_time":1.042980126,"remaining_time":10.70188303},
{"learn":[0.1383695567],"iteration":23,"passed_time":1.08522778,"remaining_time":10.62618868},
{"learn":[0.1373864548],"iteration":24,"passed_time":1.134170281,"remaining_time":10.61583383},
{"learn":[0.1364411934],"iteration":25,"passed_time":1.184843856,"remaining_time":10.61802378},
{"learn":[0.1346238099],"iteration":26,"passed_time":1.230841671,"remaining_time":10.57612103},
{"learn":[0.1334554628],"iteration":27,"passed_time":1.268893673,"remaining_time":10.4683728},
{"learn":[0.132603918],"iteration":28,"passed_time":1.306470359,"remaining_time":10.36166146},
{"learn":[0.1307801759],"iteration":29,"passed_time":1.342524144,"remaining_time":10.2479343},
{"learn":[0.1302251152],"iteration":30,"passed_time":1.374669724,"remaining_time":10.1104741},
{"learn":[0.1287029789],"iteration":31,"passed_time":1.40868993,"remaining_time":9.992894194},
{"learn":[0.127361431],"iteration":32,"passed_time":1.449495943,"remaining_time":9.926851003},
{"learn":[0.1250546016],"iteration":33,"passed_time":1.488170837,"remaining_time":9.848189362},
{"learn":[0.1240462968],"iteration":34,"passed_time":1.526953682,"remaining_time":9.772503565},
{"learn":[0.1231398957],"iteration":35,"passed_time":1.566630924,"remaining_time":9.704408221},
{"learn":[0.1224984048],"iteration":36,"passed_time":1.612633215,"remaining_time":9.67579929},
{"learn":[0.1211252648],"iteration":37,"passed_time":1.655393607,"remaining_time":9.627420712},
{"learn":[0.1201840438],"iteration":38,"passed_time":1.697765594,"remaining_time":9.577139247},
{"learn":[0.1196955702],"iteration":39,"passed_time":1.740952974,"remaining_time":9.531717531},
{"learn":[0.1188239969],"iteration":40,"passed_time":1.775007012,"remaining_time":9.437842159},
{"learn":[0.1181186473],"iteration":41,"passed_time":1.809741085,"remaining_time":9.350328939},
{"learn":[0.1173197305],"iteration":42,"passed_time":1.845833497,"remaining_time":9.272093846},
{"learn":[0.1167833337],"iteration":43,"passed_time":1.881026625,"remaining_time":9.191380098},
{"learn":[0.1157752274],"iteration":44,"passed_time":1.915021902,"remaining_time":9.106993045},
{"learn":[0.1153550533],"iteration":45,"passed_time":1.945601365,"remaining_time":9.008980235},
{"learn":[0.1148338904],"iteration":46,"passed_time":1.980320099,"remaining_time":8.932507682},
{"learn":[0.1143082878],"iteration":47,"passed_time":2.018100055,"remaining_time":8.87123149},
{"learn":[0.1137392962],"iteration":48,"passed_time":2.057103073,"remaining_time":8.816156025},
{"learn":[0.1133169707],"iteration":49,"passed_time":2.108110138,"remaining_time":8.811900375},
{"learn":[0.1119182093],"iteration":50,"passed_time":2.170676359,"remaining_time":8.852954561},
{"learn":[0.1111636157],"iteration":51,"passed_time":2.223677878,"remaining_time":8.851948477},
{"learn":[0.1106763495],"iteration":52,"passed_time":2.267363826,"remaining_time":8.812772607},
{"learn":[0.1102285863],"iteration":53,"passed_time":2.313581851,"remaining_time":8.783042214},
{"learn":[0.1094144693],"iteration":54,"passed_time":2.360550619,"remaining_time":8.755496841},
{"learn":[0.1088964014],"iteration":55,"passed_time":2.404363641,"remaining_time":8.715818199},
{"learn":[0.1082470903],"iteration":56,"passed_time":2.445332006,"remaining_time":8.665913424},
{"learn":[0.1075067755],"iteration":57,"passed_time":2.483560864,"remaining_time":8.606822995},
{"learn":[0.1067308559],"iteration":58,"passed_time":2.530825535,"remaining_time":8.57906961},
{"learn":[0.1063003302],"iteration":59,"passed_time":2.581466851,"remaining_time":8.561865055},
{"learn":[0.1055848165],"iteration":60,"passed_time":2.622022099,"remaining_time":8.510825828},
{"learn":[0.1051338515],"iteration":61,"passed_time":2.661133264,"remaining_time":8.45553634},
{"learn":[0.1043972921],"iteration":62,"passed_time":2.702481716,"remaining_time":8.407720895},
{"learn":[0.1038089986],"iteration":63,"passed_time":2.743619007,"remaining_time":8.359464163},
{"learn":[0.1031207463],"iteration":64,"passed_time":2.794576789,"remaining_time":8.340736878},
{"learn":[0.1025449768],"iteration":65,"passed_time":2.84915608,"remaining_time":8.331623082},
{"learn":[0.1018411439],"iteration":66,"passed_time":2.927108386,"remaining_time":8.388131496},
{"learn":[0.1012313634],"iteration":67,"passed_time":2.980935821,"remaining_time":8.372922675},
{"learn":[0.1007303478],"iteration":68,"passed_time":3.025206975,"remaining_time":8.330280075},
{"learn":[0.1001573561],"iteration":69,"passed_time":3.067521994,"remaining_time":8.282309384},
{"learn":[0.0997474188],"iteration":70,"passed_time":3.114395538,"remaining_time":8.246568466},
{"learn":[0.09913116644],"iteration":71,"passed_time":3.165738547,"remaining_time":8.222126505},
{"learn":[0.09864035398],"iteration":72,"passed_time":3.210765569,"remaining_time":8.180854737},
{"learn":[0.09763439806],"iteration":73,"passed_time":3.249473105,"remaining_time":8.123682762},
{"learn":[0.09729222636],"iteration":74,"passed_time":3.285631499,"remaining_time":8.060749278},
{"learn":[0.09696106209],"iteration":75,"passed_time":3.324912689,"remaining_time":8.006039764},
{"learn":[0.09633980141],"iteration":76,"passed_time":3.361936047,"remaining_time":7.946394294},
{"learn":[0.09559494652],"iteration":77,"passed_time":3.397374964,"remaining_time":7.883652161},
{"learn":[0.09512229656],"iteration":78,"passed_time":3.437375443,"remaining_time":7.831994681},
{"learn":[0.09486205532],"iteration":79,"passed_time":3.472783528,"remaining_time":7.770353144},
{"learn":[0.09444306557],"iteration":80,"passed_time":3.510760807,"remaining_time":7.715005231},
{"learn":[0.09409579932],"iteration":81,"passed_time":3.553424848,"remaining_time":7.670197538},
{"learn":[0.09358370586],"iteration":82,"passed_time":3.592745244,"remaining_time":7.618351361},
{"learn":[0.09320306248],"iteration":83,"passed_time":3.633564374,"remaining_time":7.569925779},
{"learn":[0.09286065051],"iteration":84,"passed_time":3.680337626,"remaining_time":7.533867611},
{"learn":[0.09241511464],"iteration":85,"passed_time":3.716944821,"remaining_time":7.47710993},
{"learn":[0.09212238955],"iteration":86,"passed_time":3.754594384,"remaining_time":7.422876253},
{"learn":[0.09166988594],"iteration":87,"passed_time":3.788529898,"remaining_time":7.361802416},
{"learn":[0.09144470136],"iteration":88,"passed_time":3.821284535,"remaining_time":7.29908282},
{"learn":[0.09076884099],"iteration":89,"passed_time":3.867092012,"remaining_time":7.261539444},
{"learn":[0.09050413161],"iteration":90,"passed_time":3.904807498,"remaining_time":7.20887538},
{"learn":[0.09026431831],"iteration":91,"passed_time":3.943119824,"remaining_time":7.15761968},
{"learn":[0.09006994257],"iteration":92,"passed_time":3.979679676,"remaining_time":7.103514261},
{"learn":[0.08979208294],"iteration":93,"passed_time":4.010881662,"remaining_time":7.040377385},
{"learn":[0.08954474406],"iteration":94,"passed_time":4.039229911,"remaining_time":6.972986372},
{"learn":[0.08907759934],"iteration":95,"passed_time":4.074116487,"remaining_time":6.917510286},
{"learn":[0.08861434708],"iteration":96,"passed_time":4.106103821,"remaining_time":6.857616691},
{"learn":[0.08827278803],"iteration":97,"passed_time":4.137640411,"remaining_time":6.797552103},
{"learn":[0.08795712055],"iteration":98,"passed_time":4.17108654,"remaining_time":6.741149963},
{"learn":[0.08780884784],"iteration":99,"passed_time":4.201551289,"remaining_time":6.68046655},
{"learn":[0.08719534134],"iteration":100,"passed_time":4.236187824,"remaining_time":6.626907685},
{"learn":[0.08694132886],"iteration":101,"passed_time":4.267542432,"remaining_time":6.568668254},
{"learn":[0.08677725034],"iteration":102,"passed_time":4.291857526,"remaining_time":6.500289068},
{"learn":[0.08647113737],"iteration":103,"passed_time":4.324457614,"remaining_time":6.445105098},
{"learn":[0.08623858352],"iteration":104,"passed_time":4.357814624,"remaining_time":6.391461448},
{"learn":[0.08586475338],"iteration":105,"passed_time":4.395327116,"remaining_time":6.344198573},
{"learn":[0.08564110502],"iteration":106,"passed_time":4.429176959,"remaining_time":6.291914933},
{"learn":[0.08522481288],"iteration":107,"passed_time":4.463794589,"remaining_time":6.241046138},
{"learn":[0.084833387],"iteration":108,"passed_time":4.50273757,"remaining_time":6.196427849},
{"learn":[0.08460896616],"iteration":109,"passed_time":4.537512001,"remaining_time":6.146266255},
{"learn":[0.08426498217],"iteration":110,"passed_time":4.578936913,"remaining_time":6.105249217},
{"learn":[0.08393889061],"iteration":111,"passed_time":4.619688787,"remaining_time":6.063341533},
{"learn":[0.08354289836],"iteration":112,"passed_time":4.656565317,"remaining_time":6.016447224},
{"learn":[0.08333552785],"iteration":113,"passed_time":4.696093051,"remaining_time":5.97310081},
{"learn":[0.08313721925],"iteration":114,"passed_time":4.736393279,"remaining_time":5.930788105},
{"learn":[0.08273847868],"iteration":115,"passed_time":4.777841187,"remaining_time":5.889924912},
{"learn":[0.0824663669],"iteration":116,"passed_time":4.82176491,"remaining_time":5.852056557},
{"learn":[0.08215860912],"iteration":117,"passed_time":4.86377019,"remaining_time":5.811793193},
{"learn":[0.08172953141],"iteration":118,"passed_time":4.941533328,"remaining_time":5.813568622},
{"learn":[0.08133640819],"iteration":119,"passed_time":5.015869079,"remaining_time":5.81004835},
{"learn":[0.08116581163],"iteration":120,"passed_time":5.072038715,"remaining_time":5.784639196},
{"learn":[0.08089403088],"iteration":121,"passed_time":5.118893151,"remaining_time":5.74826526},
{"learn":[0.08064013147],"iteration":122,"passed_time":5.178084539,"remaining_time":5.725361766},
{"learn":[0.08056302846],"iteration":123,"passed_time":5.205380107,"remaining_time":5.667147697},
{"learn":[0.08027583845],"iteration":124,"passed_time":5.254162311,"remaining_time":5.632461998},
{"learn":[0.07996136934],"iteration":125,"passed_time":5.296393753,"remaining_time":5.59063785},
{"learn":[0.07978112444],"iteration":126,"passed_time":5.333192747,"remaining_time":5.543160966},
{"learn":[0.07927764017],"iteration":127,"passed_time":5.378824302,"remaining_time":5.504890497},
{"learn":[0.0790547563],"iteration":128,"passed_time":5.419180584,"remaining_time":5.461189736},
{"learn":[0.0787691357],"iteration":129,"passed_time":5.461025544,"remaining_time":5.419017655},
{"learn":[0.07855314015],"iteration":130,"passed_time":5.500912456,"remaining_time":5.374937362},
{"learn":[0.07820375845],"iteration":131,"passed_time":5.542817483,"remaining_time":5.332862275},
{"learn":[0.07795409201],"iteration":132,"passed_time":5.582154138,"remaining_time":5.288356552},
{"learn":[0.07781474136],"iteration":133,"passed_time":5.619864111,"remaining_time":5.242410552},
{"learn":[0.0774710833],"iteration":134,"passed_time":5.660869808,"remaining_time":5.199613749},
{"learn":[0.07724059028],"iteration":135,"passed_time":5.697938624,"remaining_time":5.153282726},
{"learn":[0.0770550597],"iteration":136,"passed_time":5.737386283,"remaining_time":5.109205303},
{"learn":[0.07683984333],"iteration":137,"passed_time":5.778271192,"remaining_time":5.066455175},
{"learn":[0.07666835504],"iteration":138,"passed_time":5.820348461,"remaining_time":5.024761261},
{"learn":[0.07639161723],"iteration":139,"passed_time":5.86212097,"remaining_time":4.982802825},
{"learn":[0.07603913193],"iteration":140,"passed_time":5.903811714,"remaining_time":4.940778597},
{"learn":[0.07576561673],"iteration":141,"passed_time":5.939033072,"remaining_time":4.893428658},
{"learn":[0.075500411],"iteration":142,"passed_time":5.976774092,"remaining_time":4.848292271},
{"learn":[0.07538978316],"iteration":143,"passed_time":6.004846296,"remaining_time":4.795536972},
{"learn":[0.07502411013],"iteration":144,"passed_time":6.039044845,"remaining_time":4.747938706},
{"learn":[0.07494030479],"iteration":145,"passed_time":6.071895498,"remaining_time":4.699480762},
{"learn":[0.07472922528],"iteration":146,"passed_time":6.109499763,"remaining_time":4.654856962},
{"learn":[0.07463718901],"iteration":147,"passed_time":6.142623159,"remaining_time":4.606967369},
{"learn":[0.07444556985],"iteration":148,"passed_time":6.17545063,"remaining_time":4.559057512},
{"learn":[0.07416183437],"iteration":149,"passed_time":6.211154149,"remaining_time":4.513438682},
{"learn":[0.0739017273],"iteration":150,"passed_time":6.246002775,"remaining_time":4.467339733},
{"learn":[0.07357331019],"iteration":151,"passed_time":6.283627996,"remaining_time":4.423343392},
{"learn":[0.07332680703],"iteration":152,"passed_time":6.318898241,"remaining_time":4.377798782},
{"learn":[0.07317444099],"iteration":153,"passed_time":6.35324093,"remaining_time":4.33175518},
{"learn":[0.07296324444],"iteration":154,"passed_time":6.390618104,"remaining_time":4.287898599},
{"learn":[0.07273265925],"iteration":155,"passed_time":6.42792643,"remaining_time":4.24407963},
{"learn":[0.07238511657],"iteration":156,"passed_time":6.461695532,"remaining_time":4.198044231},
{"learn":[0.07214357991],"iteration":157,"passed_time":6.499723384,"remaining_time":4.154886467},
{"learn":[0.0719010141],"iteration":158,"passed_time":6.53996349,"remaining_time":4.113184585},
{"learn":[0.07149356932],"iteration":159,"passed_time":6.579133399,"remaining_time":4.070838791},
{"learn":[0.07126996882],"iteration":160,"passed_time":6.623896122,"remaining_time":4.03193677},
{"learn":[0.07118440786],"iteration":161,"passed_time":6.670315753,"remaining_time":3.993954494},
{"learn":[0.07096311099],"iteration":162,"passed_time":6.70942338,"remaining_time":3.951562236},
{"learn":[0.07087650721],"iteration":163,"passed_time":6.748790371,"remaining_time":3.909360276},
{"learn":[0.07060920063],"iteration":164,"passed_time":6.788460573,"remaining_time":3.867365417},
{"learn":[0.07041165695],"iteration":165,"passed_time":6.828634014,"remaining_time":3.825680502},
{"learn":[0.07019920645],"iteration":166,"passed_time":6.876012167,"remaining_time":3.78798275},
{"learn":[0.06995778348],"iteration":167,"passed_time":6.924741243,"remaining_time":3.750901507},
{"learn":[0.06976056889],"iteration":168,"passed_time":6.967329321,"remaining_time":3.710412064},
{"learn":[0.06949560361],"iteration":169,"passed_time":7.006556421,"remaining_time":3.668138362},
{"learn":[0.06919548325],"iteration":170,"passed_time":7.039623507,"remaining_time":3.622730226},
{"learn":[0.0689607979],"iteration":171,"passed_time":7.073175632,"remaining_time":3.57771093},
{"learn":[0.06883631099],"iteration":172,"passed_time":7.104157273,"remaining_time":3.53154639},
{"learn":[0.06857729661],"iteration":173,"passed_time":7.139693127,"remaining_time":3.487781125},
{"learn":[0.06835257857],"iteration":174,"passed_time":7.17513444,"remaining_time":3.444064531},
{"learn":[0.06821545157],"iteration":175,"passed_time":7.211390845,"remaining_time":3.400826365},
{"learn":[0.06814563668],"iteration":176,"passed_time":7.248547326,"remaining_time":3.358084072},
{"learn":[0.06796745465],"iteration":177,"passed_time":7.2877149,"remaining_time":3.316319702},
{"learn":[0.06776050633],"iteration":178,"passed_time":7.330391512,"remaining_time":3.276152631},
{"learn":[0.06752094265],"iteration":179,"passed_time":7.371292707,"remaining_time":3.235178466},
{"learn":[0.06732202517],"iteration":180,"passed_time":7.408555775,"remaining_time":3.192637295},
{"learn":[0.06716771307],"iteration":181,"passed_time":7.446469235,"remaining_time":3.150429292},
{"learn":[0.06698085643],"iteration":182,"passed_time":7.505532307,"remaining_time":3.117051669},
{"learn":[0.06674197631],"iteration":183,"passed_time":7.563479545,"remaining_time":3.082940032},
{"learn":[0.06668351488],"iteration":184,"passed_time":7.59259191,"remaining_time":3.037036764},
{"learn":[0.06640866959],"iteration":185,"passed_time":7.633912467,"remaining_time":2.99610543},
{"learn":[0.06610603964],"iteration":186,"passed_time":7.677340733,"remaining_time":2.955981459},
{"learn":[0.06596613417],"iteration":187,"passed_time":7.713401062,"remaining_time":2.913039763},
{"learn":[0.06587954033],"iteration":188,"passed_time":7.74796887,"remaining_time":2.8696181},
{"learn":[0.06566598887],"iteration":189,"passed_time":7.785392357,"remaining_time":2.827326698},
{"learn":[0.06564831514],"iteration":190,"passed_time":7.817622925,"remaining_time":2.783237481},
{"learn":[0.06532132183],"iteration":191,"passed_time":7.851169884,"remaining_time":2.739731158},
{"learn":[0.06523906469],"iteration":192,"passed_time":7.882780311,"remaining_time":2.695665806},
{"learn":[0.06485780604],"iteration":193,"passed_time":7.918976504,"remaining_time":2.653265323},
{"learn":[0.06465798094],"iteration":194,"passed_time":7.950300402,"remaining_time":2.609329363},
{"learn":[0.06451724243],"iteration":195,"passed_time":7.984965488,"remaining_time":2.56659605},
{"learn":[0.06439312371],"iteration":196,"passed_time":8.020764053,"remaining_time":2.524301377},
{"learn":[0.06427287027],"iteration":197,"passed_time":8.048220307,"remaining_time":2.479502216},
{"learn":[0.06421120631],"iteration":198,"passed_time":8.07810435,"remaining_time":2.435609352},
{"learn":[0.06402713375],"iteration":199,"passed_time":8.112086575,"remaining_time":2.39306554},
{"learn":[0.06385944291],"iteration":200,"passed_time":8.145034865,"remaining_time":2.350308568},
{"learn":[0.06368144098],"iteration":201,"passed_time":8.178690094,"remaining_time":2.307848195},
{"learn":[0.06350853667],"iteration":202,"passed_time":8.212671263,"remaining_time":2.265564486},
{"learn":[0.0633111514],"iteration":203,"passed_time":8.243749638,"remaining_time":2.222579559},
{"learn":[0.06307207965],"iteration":204,"passed_time":8.280685119,"remaining_time":2.181253641},
{"learn":[0.06288608549],"iteration":205,"passed_time":8.320510885,"remaining_time":2.140713966},
{"learn":[0.06261926693],"iteration":206,"passed_time":8.362966716,"remaining_time":2.10084188},
{"learn":[0.06242535827],"iteration":207,"passed_time":8.411271278,"remaining_time":2.062379015},
{"learn":[0.06227084804],"iteration":208,"passed_time":8.441960759,"remaining_time":2.019607837},
{"learn":[0.06217066691],"iteration":209,"passed_time":8.473784558,"remaining_time":1.977216397},
{"learn":[0.06198218393],"iteration":210,"passed_time":8.508883023,"remaining_time":1.935670072},
{"learn":[0.06180488355],"iteration":211,"passed_time":8.544268877,"remaining_time":1.894248289},
{"learn":[0.06145132423],"iteration":212,"passed_time":8.579573994,"remaining_time":1.852865745},
{"learn":[0.06122857215],"iteration":213,"passed_time":8.613912116,"remaining_time":1.81133666},
{"learn":[0.06102615371],"iteration":214,"passed_time":8.648266757,"remaining_time":1.769877848},
{"learn":[0.06090907959],"iteration":215,"passed_time":8.68369859,"remaining_time":1.728699256},
{"learn":[0.0607679638],"iteration":216,"passed_time":8.720728027,"remaining_time":1.687882844},
{"learn":[0.06067265818],"iteration":217,"passed_time":8.752321955,"remaining_time":1.6460789},
{"learn":[0.06047456593],"iteration":218,"passed_time":8.785267978,"remaining_time":1.604615156},
{"learn":[0.06030213492],"iteration":219,"passed_time":8.81426146,"remaining_time":1.562528168},
{"learn":[0.06019805651],"iteration":220,"passed_time":8.843717682,"remaining_time":1.520639239},
{"learn":[0.06002330126],"iteration":221,"passed_time":8.874293952,"remaining_time":1.479048992},
{"learn":[0.05981055533],"iteration":222,"passed_time":8.90735459,"remaining_time":1.437958588},
{"learn":[0.05953246239],"iteration":223,"passed_time":8.939439081,"remaining_time":1.396787356},
{"learn":[0.05938937367],"iteration":224,"passed_time":8.970437643,"remaining_time":1.355532799},
{"learn":[0.0591708494],"iteration":225,"passed_time":9.004337691,"remaining_time":1.314792672},
{"learn":[0.05898883597],"iteration":226,"passed_time":9.038005014,"remaining_time":1.274080002},
{"learn":[0.05878651341],"iteration":227,"passed_time":9.070200288,"remaining_time":1.233228987},
{"learn":[0.05863057365],"iteration":228,"passed_time":9.109876047,"remaining_time":1.193433543},
{"learn":[0.05843414635],"iteration":229,"passed_time":9.156857574,"remaining_time":1.154560303},
{"learn":[0.05830710682],"iteration":230,"passed_time":9.203547397,"remaining_time":1.115581503},
{"learn":[0.05816291441],"iteration":231,"passed_time":9.242957525,"remaining_time":1.075689022},
{"learn":[0.05798149671],"iteration":232,"passed_time":9.280718621,"remaining_time":1.03561667},
{"learn":[0.05788789778],"iteration":233,"passed_time":9.316721312,"remaining_time":0.9953762086},
{"learn":[0.0578716415],"iteration":234,"passed_time":9.348525948,"remaining_time":0.9547430755},
{"learn":[0.05764683879],"iteration":235,"passed_time":9.385449515,"remaining_time":0.9146836392},
{"learn":[0.05748868499],"iteration":236,"passed_time":9.417688058,"remaining_time":0.8742157691},
{"learn":[0.05737918521],"iteration":237,"passed_time":9.448671071,"remaining_time":0.8337062709},
{"learn":[0.05727678863],"iteration":238,"passed_time":9.484381192,"remaining_time":0.7936720663},
{"learn":[0.05707479251],"iteration":239,"passed_time":9.515636189,"remaining_time":0.7533211983},
{"learn":[0.05698346646],"iteration":240,"passed_time":9.547550795,"remaining_time":0.7130950801},
{"learn":[0.05681714146],"iteration":241,"passed_time":9.580564092,"remaining_time":0.6730148329},
{"learn":[0.05663297928],"iteration":242,"passed_time":9.612559928,"remaining_time":0.6329257566},
{"learn":[0.05644473993],"iteration":243,"passed_time":9.64216081,"remaining_time":0.5927557875},
{"learn":[0.05628517249],"iteration":244,"passed_time":9.671861057,"remaining_time":0.5526777747},
{"learn":[0.05615406787],"iteration":245,"passed_time":9.70379281,"remaining_time":0.5128020591},
{"learn":[0.05599246831],"iteration":246,"passed_time":9.734462086,"remaining_time":0.4729293321},
{"learn":[0.05588848052],"iteration":247,"passed_time":9.769340612,"remaining_time":0.4333175272},
{"learn":[0.05574345263],"iteration":248,"passed_time":9.806757763,"remaining_time":0.3938456933},
{"learn":[0.0555970508],"iteration":249,"passed_time":9.845475528,"remaining_time":0.354437119},
{"learn":[0.05531698343],"iteration":250,"passed_time":9.886769211,"remaining_time":0.3151161502},
{"learn":[0.05514685211],"iteration":251,"passed_time":9.926304065,"remaining_time":0.2757306685},
{"learn":[0.05505827902],"iteration":252,"passed_time":9.959213291,"remaining_time":0.2361868765},
{"learn":[0.05494450597],"iteration":253,"passed_time":9.993888966,"remaining_time":0.1967300978},
{"learn":[0.05474002401],"iteration":254,"passed_time":10.033267,"remaining_time":0.1573845804},
{"learn":[0.05453222866],"iteration":255,"passed_time":10.06859553,"remaining_time":0.1179913539},
{"learn":[0.0544060639],"iteration":256,"passed_time":10.10675469,"remaining_time":0.07865178745},
{"learn":[0.05429895956],"iteration":257,"passed_time":10.14277972,"remaining_time":0.03931309969},
{"learn":[0.05415435567],"iteration":258,"passed_time":10.17661376,"remaining_time":0}
]}